src/__init__.py
src/data/__init__.py
src/data/make_dataset.py
src/features/__init__.py
src/features/build_features.py
src/models/__init__.py
src/models/predict_model.py
src/models/train_model.py
src/visualization/__init__.py
src/visualization/visualize.py
LazyEDA-0.1.0.dist-info/LICENSE
LazyEDA-0.1.0.dist-info/METADATA
LazyEDA-0.1.0.dist-info/WHEEL
LazyEDA-0.1.0.dist-info/top_level.txt
LazyEDA-0.1.0.dist-info/RECORD
