Metadata-Version: 2.1
Name: LazyEDA
Version: 0.1.0
Summary: Lazy EDA is a python library too help shorten the coding time for basic understanding  of data, EDA techniques and repetitive tasks with less lines of code
Home-page: https://gitlab.com/shankarpandala/lazyeda
Author: Shankar Rao Pandala
License: MIT
Platform: UNKNOWN
Classifier: Programming Language :: Python :: 3
